README.rst
setup.cfg
setup.py
h9/__init__.py
h9.egg-info/PKG-INFO
h9.egg-info/SOURCES.txt
h9.egg-info/dependency_links.txt
h9.egg-info/requires.txt
h9.egg-info/top_level.txt