Metadata-Version: 1.2
Name: h9
Version: 0.0.0
Summary: h9 utils library
Home-page: https://github.com/sq8kfh/pyh9
Author: SQ8KFH
Author-email: sq8kfh@gmail.com
License: MIT
Keywords: h9
Platform: UNKNOWN
Classifier: Development Status :: 3 - Alpha
Classifier: Intended Audience :: Developers
Classifier: Topic :: Software Development :: Libraries :: Python Modules
Classifier: License :: OSI Approved :: MIT License
Classifier: Programming Language :: Python :: 3 :: Only
Classifier: Programming Language :: Python :: 3.5
Classifier: Programming Language :: Python :: 3.6
Requires-Python: >=3.5
